humancat/__init__.py
humancat/cat.py
humancat/human.py
humancat2-0.0.5.dist-info/METADATA
humancat2-0.0.5.dist-info/WHEEL
humancat2-0.0.5.dist-info/top_level.txt
humancat2-0.0.5.dist-info/RECORD
